line_works_board/__init__.py
line_works_board/auth.py
line_works_board/board.py
line_works_board/py.typed
line_works_board/types.py
line_works_board-0.1.1.dist-info/METADATA
line_works_board-0.1.1.dist-info/WHEEL
line_works_board-0.1.1.dist-info/RECORD
