Metadata-Version: 2.4
Name: line-works-board
Version: 0.1.1
Summary: LINE WORKS掲示板APIのPython SDK
Requires-Python: >=3.10
Requires-Dist: cryptography>=41.0.0
Requires-Dist: dotenv>=0.9.9
Requires-Dist: pandas>=2.3.2
Requires-Dist: pyjwt>=2.8.0
Requires-Dist: python-dotenv>=1.0.0
Requires-Dist: requests>=2.31.0
